tservice/__init__.py
tservice/cli.py
tservice/tservice.py
tservice-1.0.0.dist-info/DESCRIPTION.rst
tservice-1.0.0.dist-info/entry_points.txt
tservice-1.0.0.dist-info/METADATA
tservice-1.0.0.dist-info/metadata.json
tservice-1.0.0.dist-info/RECORD
tservice-1.0.0.dist-info/top_level.txt
tservice-1.0.0.dist-info/WHEEL
