Metadata-Version: 2.0
Name: tservice
Version: 1.0.0
Summary: Quick static file server
Home-page: https://jiffyclub.github.io/tservice/
Author: Matt Davis
Author-email: jiffyclub@gmail.com
License: UNKNOWN
Platform: UNKNOWN
Classifier: License :: OSI Approved :: ISC License (ISCL)
Classifier: Programming Language :: Python
Classifier: Programming Language :: Python :: 2.7
Classifier: Programming Language :: Python :: 3
Requires-Dist: tornado (>=4.0)
